pmsampsize/__init__.py
pmsampsize/pmsampsize.py
pmsampsize-0.1.0.dist-info/LICENSE
pmsampsize-0.1.0.dist-info/METADATA
pmsampsize-0.1.0.dist-info/WHEEL
pmsampsize-0.1.0.dist-info/RECORD
