Metadata-Version: 2.1
Name: pmsampsize
Version: 0.1.0
Summary: Sample size for development of a prediction model.
License: GNU General Public License v3.0
Author: Rebecca Whittle & Joie Ensor
Requires-Python: >=3.12,<4.0
Classifier: License :: Other/Proprietary License
Classifier: Programming Language :: Python :: 3
Classifier: Programming Language :: Python :: 3.12
Requires-Dist: numpy (>=2.3.3,<3.0.0)
Requires-Dist: pandas (>=2.3.2,<3.0.0)
Requires-Dist: scipy (>=1.16.2,<2.0.0)
Requires-Dist: statsmodels (>=0.14.5,<0.15.0)
Requires-Dist: tabulate (>=0.9.0,<0.10.0)
